README.md
setup.cfg
setup.py
dsnd_distribution_LB/Binomialdistribution.py
dsnd_distribution_LB/Gaussiandistribution.py
dsnd_distribution_LB/Generaldistribution.py
dsnd_distribution_LB/__init__.py
dsnd_distribution_LB.egg-info/PKG-INFO
dsnd_distribution_LB.egg-info/SOURCES.txt
dsnd_distribution_LB.egg-info/dependency_links.txt
dsnd_distribution_LB.egg-info/not-zip-safe
dsnd_distribution_LB.egg-info/top_level.txt